otk_interactive/__init__.py
otk_interactive/__version__.py
otk_interactive/otk.py
otk_interactive-0.3.3.dist-info/LICENSE
otk_interactive-0.3.3.dist-info/METADATA
otk_interactive-0.3.3.dist-info/WHEEL
otk_interactive-0.3.3.dist-info/RECORD
