Metadata-Version: 2.3
Name: otk_interactive
Version: 0.3.3
Summary: 
License: MIT
Author: Kennete Basco
Author-email: 97374837+kankenny@users.noreply.github.com
Requires-Python: >=3.10,<3.13
Classifier: License :: OSI Approved :: MIT License
Classifier: Programming Language :: Python :: 3
Classifier: Programming Language :: Python :: 3.10
Classifier: Programming Language :: Python :: 3.11
Classifier: Programming Language :: Python :: 3.12
Requires-Dist: optical-toolkit (>=1.3.0,<2.0.0)
Requires-Dist: pandas (>=2.2.3,<3.0.0)
Requires-Dist: plotly (>=6.0.1,<7.0.0)
Requires-Dist: tensorflow-io-gcs-filesystem (==0.37.1)
